asolut/__init__.py
asolut/main.py
asolut/web/main.html
asolut/web/main_css.css
asolut/web/main_js.js
asolut/web/fonts/LICENSE.txt
asolut/web/fonts/OpenSans-Light.ttf
asolut/web/fonts/OpenSans-Regular.ttf
asolut/web/fonts/OpenSans-SemiBold.ttf
asolut/web/images/arr.svg
asolut/web/images/favicon.ico
asolut/web/images/gear.svg
asolut/web/images/loadinggear.svg
asolut/web/images/logo.png
asolut/web/images/que.svg
asolut-1.2.13.dist-info/LICENSE
asolut-1.2.13.dist-info/METADATA
asolut-1.2.13.dist-info/WHEEL
asolut-1.2.13.dist-info/top_level.txt
asolut-1.2.13.dist-info/RECORD
